AUTHORS
LICENSE
MANIFEST.in
README.rst
setup.py
cbv_formpreview/__init__.py
cbv_formpreview/models.py
cbv_formpreview/preview.py
cbv_formpreview/templates/cbv_formpreview/base.html
cbv_formpreview/templates/cbv_formpreview/form.html
cbv_formpreview/templates/cbv_formpreview/preview.html
cbv_formpreview/tests/__init__.py
cbv_formpreview/tests/models.py
cbv_formpreview/tests/runtests.py
cbv_formpreview/tests/tests.py
cbv_formpreview/tests/urls.py
django_cbv_formpreview.egg-info/PKG-INFO
django_cbv_formpreview.egg-info/SOURCES.txt
django_cbv_formpreview.egg-info/dependency_links.txt
django_cbv_formpreview.egg-info/not-zip-safe
django_cbv_formpreview.egg-info/top_level.txt