Metadata-Version: 1.0
Name: django-cbv-formpreview
Version: 0.2.0a1
Summary: Django's FormPreview updated to use class based views.
Home-page: https://github.com/ryankask/django-cbv-formpreview
Author: Ryan Kaskel
Author-email: dev@ryankaskel.com
License: BSD
Platform: UNKNOWN
Classifier: Environment :: Web Environment
Classifier: Development Status :: 3 - Alpha
Classifier: Intended Audience :: Developers
Classifier: License :: OSI Approved :: BSD License
Classifier: Operating System :: OS Independent
Classifier: Programming Language :: Python
Classifier: Framework :: Django
